{
  "type": "object",
  "properties": {
    "Areas": {
      "description": "Array of map areas that all use the same particle",
      "type": "array",
      "items": {
        "type": "object",
        "properties": {
          "package": {
            "type": "string"
          },
          "name": {
            "type": "string"
          }
        },
        "required": [
          "name",
          "package"
        ]
      }
    },
    "Particle": {
      "description": "Particle associated with map areas"
    }
  },
  "required": [
    "Areas",
    "Particle"
  ]
}