{
  "type": "object",
  "properties": {
    "GamePhase": {
      "$ref": "#/definitions/EGamePhase",
      "description": "The phase to specify tier for"
    },
    "LastTierOfPhase": {
      "description": "What is the last tier of the phase specified previously.",
      "type": "number"
    },
    "Name": {
      "description": "Name of this phase.",
      "type": "string"
    },
    "PhaseUnlockedMessage": {
      "description": "Message sent when this phase is unlocked",
      "type": "object",
      "properties": {
        "package": {
          "type": "string"
        },
        "name": {
          "type": "string"
        }
      },
      "required": [
        "name",
        "package"
      ]
    }
  },
  "required": [
    "GamePhase",
    "LastTierOfPhase",
    "Name",
    "PhaseUnlockedMessage"
  ]
}